django_haystack_channels-0.0.3.dist-info/DESCRIPTION.rst
django_haystack_channels-0.0.3.dist-info/METADATA
django_haystack_channels-0.0.3.dist-info/RECORD
django_haystack_channels-0.0.3.dist-info/WHEEL
django_haystack_channels-0.0.3.dist-info/metadata.json
django_haystack_channels-0.0.3.dist-info/top_level.txt
haystack_channels/__init__.py
haystack_channels/routing.py
haystack_channels/signals.py
