Metadata-Version: 2.0
Name: django-haystack-channels
Version: 0.0.3
Summary: Helper code to connect Haystack to Django Channels
Home-page: https://github.com/LegoStormtroopr/django-haystack-channels
Author: Samuel Spencer
Author-email: sam@aristotlemetadata.com
License: BSD Licence
Platform: UNKNOWN
Classifier: Development Status :: 3 - Alpha
Classifier: Environment :: Web Environment
Classifier: Framework :: Django
Classifier: Intended Audience :: Information Technology
Classifier: Operating System :: OS Independent
Classifier: Programming Language :: Python
Classifier: Programming Language :: Python :: 2
Classifier: Programming Language :: Python :: 3
Classifier: Topic :: Internet :: WWW/HTTP
Classifier: Topic :: Internet :: WWW/HTTP :: Dynamic Content
Requires-Dist: Django
Requires-Dist: channels
Requires-Dist: django-haystack
